wavelets/__init__.py
wavelets/coiflet.py
wavelets/db.py
wavelets/haar.py
wavelets/io.py
wavelets/lifting_step.py
wavelets/main.py
wavelets/misc.py
wavelets/symlets.py
wavelets/transform.py
integer_wavelets-0.4.0.dist-info/LICENSE
integer_wavelets-0.4.0.dist-info/METADATA
integer_wavelets-0.4.0.dist-info/WHEEL
integer_wavelets-0.4.0.dist-info/entry_points.txt
integer_wavelets-0.4.0.dist-info/RECORD
