Metadata-Version: 2.1
Name: integer-wavelets
Version: 0.4.0
Summary: 
Author: Bruno Petrus
Author-email: brunoxpetrus@gmail.com
Requires-Python: >=3.11,<4.0
Classifier: Programming Language :: Python :: 3
Classifier: Programming Language :: Python :: 3.11
Classifier: Programming Language :: Python :: 3.12
Requires-Dist: matplotlib (>=3.8.3,<4.0.0)
Requires-Dist: numpy (>=1.26,<2.0)
Requires-Dist: pillow (>=10.2.0,<11.0.0)
Requires-Dist: scipy (>=1.13,<2.0)
Requires-Dist: tifffile (>=2024.4.18,<2025.0.0)
